calisp/__init__.py
calisp/calisp_compute_medians.py
calisp/calisp_filter_patterns.py
calisp/data_store.py
calisp/element_count_and_mass_utils.py
calisp/isotope_matrix.txt
calisp/isotopic_pattern_utils.py
calisp/log.py
calisp/main.py
calisp/peptide_spectrum_match_files.py
calisp/unimod.py
calisp-3.1.4.dist-info/licenses/LICENSE.txt
calisp-3.1.4.dist-info/METADATA
calisp-3.1.4.dist-info/WHEEL
calisp-3.1.4.dist-info/entry_points.txt
calisp-3.1.4.dist-info/top_level.txt
calisp-3.1.4.dist-info/RECORD
