Metadata-Version: 2.4
Name: calisp
Version: 3.1.4
Summary: Isotope analysis of proteomics data
Home-page: https://github.com/kinestetika/Calisp
Author: Marc Strous
Author-email: mstrous@ucalgary.ca
License: MIT
Project-URL: Source, https://github.com/kinestetika/Calisp
Keywords: proteomics isotope mass-spectrometry 13C
Classifier: Development Status :: 4 - Beta
Classifier: Environment :: Console
Classifier: Natural Language :: English
Classifier: Operating System :: OS Independent
Classifier: License :: OSI Approved :: MIT License
Classifier: Programming Language :: Python :: 3.9
Classifier: Topic :: Scientific/Engineering :: Bio-Informatics
Requires-Python: >=3.6
License-File: LICENSE.txt
Requires-Dist: numpy
Requires-Dist: scipy
Requires-Dist: pandas
Requires-Dist: tqdm
Requires-Dist: pymzml
Requires-Dist: pyarrow
Provides-Extra: dev
Requires-Dist: setuptools; extra == "dev"
Requires-Dist: build; extra == "dev"
Requires-Dist: twine; extra == "dev"
Provides-Extra: test
Requires-Dist: jupyter; extra == "test"
Requires-Dist: matplotlib; extra == "test"
Requires-Dist: jinja2; extra == "test"
Dynamic: author
Dynamic: author-email
Dynamic: classifier
Dynamic: description
Dynamic: description-content-type
Dynamic: home-page
Dynamic: keywords
Dynamic: license
Dynamic: license-file
Dynamic: project-url
Dynamic: provides-extra
Dynamic: requires-dist
Dynamic: requires-python
Dynamic: summary
